{
  "type": "patient-registration",
  "data": {
    "last_name": "Oo0Olaf lllllllla",
    "first_name": "X20948297%|",
    "title": null,
    "patient_id": null,
    "date_of_birth": null,
    "sex": null,
    "age": null,
    "age_unit": "Years",
    "height": null,
    "height_unit": "ft",
    "weight": null,
    "weight_unit": "lbs",
    "metric": null,
    "additional_info": null,
    "accession_no": null,
    "request_id": null,
    "patient_position": null,
    "institution_name": null,
    "performing_physician": null,
    "operator": null,
    "referring_physician": null,
    "requesting_physician": null,
    "admission_id": null
  }
}